user_management/__init__.py
user_management/api/__init__.py
user_management/api/authentication.py
user_management/api/exceptions.py
user_management/api/models.py
user_management/api/permissions.py
user_management/api/serializers.py
user_management/api/throttling.py
user_management/api/views.py
user_management/api/avatar/__init__.py
user_management/api/avatar/serializers.py
user_management/api/avatar/views.py
user_management/api/avatar/tests/__init__.py
user_management/api/avatar/tests/test_serializers.py
user_management/api/avatar/tests/test_urls.py
user_management/api/avatar/tests/test_views.py
user_management/api/avatar/urls/__init__.py
user_management/api/avatar/urls/profile_avatar.py
user_management/api/avatar/urls/user_avatar.py
user_management/api/management/__init__.py
user_management/api/management/commands/__init__.py
user_management/api/management/commands/remove_expired_tokens.py
user_management/api/templates/user_management/account_validation_email.html
user_management/api/templates/user_management/account_validation_email.txt
user_management/api/templates/user_management/password_reset_email.html
user_management/api/templates/user_management/password_reset_email.txt
user_management/api/tests/__init__.py
user_management/api/tests/test_authentication.py
user_management/api/tests/test_exceptions.py
user_management/api/tests/test_management_commands.py
user_management/api/tests/test_models.py
user_management/api/tests/test_serializers.py
user_management/api/tests/test_throttling.py
user_management/api/tests/test_urls.py
user_management/api/tests/test_views.py
user_management/api/tests/urls.py
user_management/api/urls/__init__.py
user_management/api/urls/auth.py
user_management/api/urls/password_reset.py
user_management/api/urls/profile.py
user_management/api/urls/register.py
user_management/api/urls/users.py
user_management/api/urls/verify_email.py
user_management/models/__init__.py
user_management/models/admin.py
user_management/models/admin_forms.py
django_user_management-18.0.0.dist-info/LICENSE
django_user_management-18.0.0.dist-info/METADATA
django_user_management-18.0.0.dist-info/WHEEL
django_user_management-18.0.0.dist-info/top_level.txt
django_user_management-18.0.0.dist-info/RECORD
