Metadata-Version: 2.1
Name: django-user-management
Version: 18.0.0
Summary: User management model mixins and api views.
Home-page: https://github.com/incuna/django-user-management/
Author: Incuna
Author-email: admin@incuna.com
License: BSD
Keywords: django rest framework user management api
Platform: UNKNOWN
Classifier: Development Status :: 5 - Production/Stable
Classifier: Environment :: Web Environment
Classifier: Framework :: Django
Classifier: Intended Audience :: Developers
Classifier: License :: OSI Approved :: BSD License
Classifier: Programming Language :: Python :: 3
Classifier: Programming Language :: Python :: 3.6
Classifier: Programming Language :: Python :: 3.7
Classifier: Programming Language :: Python :: 3.8
Classifier: Topic :: Software Development
Classifier: Topic :: Utilities
Provides-Extra: utils
Provides-Extra: avatar
